{
    "title" : "SWI2",
    "abstract" : "SWI2 Soil water index level 2.",
    "projection": {},
    "producer": "SWI",
    "source":"grid",
    "views": [{
        "layers": [{
            "qid": "l",
            "layer_type": "isoband",
            "isobands": "json:isobands/SWI-M3M3.json",
            "css": "isobands/SWI-M3M3.css",
            "parameter": "SWI2:SWI:5029:1:0:0",
	    "sampling": { 
		"relativeresolution": 4
	    },
            "attributes": {
                "shape-rendering": "crispEdges"
            }
        }]
    }]
}
